CHANGES.txt
MANIFEST.in
README.txt
development.ini
message-extraction.ini
production.ini
setup.cfg
setup.py
pyramid_promosite/__init__.py
pyramid_promosite/security.py
pyramid_promosite/tests.py
pyramid_promosite.egg-info/PKG-INFO
pyramid_promosite.egg-info/SOURCES.txt
pyramid_promosite.egg-info/dependency_links.txt
pyramid_promosite.egg-info/entry_points.txt
pyramid_promosite.egg-info/not-zip-safe
pyramid_promosite.egg-info/requires.txt
pyramid_promosite.egg-info/top_level.txt
pyramid_promosite/models/__init__.py
pyramid_promosite/models/auth.py
pyramid_promosite/scripts/__init__.py
pyramid_promosite/scripts/initializedb.py
pyramid_promosite/static/css/style.css
pyramid_promosite/static/easyui/changelog.txt
pyramid_promosite/static/easyui/easyloader.js
pyramid_promosite/static/easyui/jquery-1.8.0.min.js
pyramid_promosite/static/easyui/jquery.easyui.min.js
pyramid_promosite/static/easyui/licence_gpl.txt
pyramid_promosite/static/easyui/license_commercial.txt
pyramid_promosite/static/easyui/readme.txt
pyramid_promosite/static/easyui/demo/accordion.html
pyramid_promosite/static/easyui/demo/calendar.html
pyramid_promosite/static/easyui/demo/combo.html
pyramid_promosite/static/easyui/demo/combobox.html
pyramid_promosite/static/easyui/demo/combogrid.html
pyramid_promosite/static/easyui/demo/combotree.html
pyramid_promosite/static/easyui/demo/datagrid.html
pyramid_promosite/static/easyui/demo/datagrid2.html
pyramid_promosite/static/easyui/demo/datagrid3.html
pyramid_promosite/static/easyui/demo/datagrid4.html
pyramid_promosite/static/easyui/demo/datagrid5.html
pyramid_promosite/static/easyui/demo/datebox.html
pyramid_promosite/static/easyui/demo/datetimebox.html
pyramid_promosite/static/easyui/demo/demo.css
pyramid_promosite/static/easyui/demo/dialog.html
pyramid_promosite/static/easyui/demo/draggable.html
pyramid_promosite/static/easyui/demo/droppable.html
pyramid_promosite/static/easyui/demo/droppable1.html
pyramid_promosite/static/easyui/demo/droppable2.html
pyramid_promosite/static/easyui/demo/easyloader.html
pyramid_promosite/static/easyui/demo/form.html
pyramid_promosite/static/easyui/demo/layout.html
pyramid_promosite/static/easyui/demo/layout1.html
pyramid_promosite/static/easyui/demo/layout2.html
