Metadata-Version: 1.1
Name: pyramid-promosite
Version: 0.0
Summary: pyramid_promosite
Home-page: http://github.com/uralbash/pyramid_promosite
Author: Svintsov Dmitry
Author-email: spam@19216801.ru
License: UNKNOWN
Keywords: web wsgi bfg pylons pyramid
Platform: UNKNOWN
Classifier: Programming Language :: Python
Classifier: Framework :: Pylons
Classifier: Topic :: Internet :: WWW/HTTP
Classifier: Topic :: Internet :: WWW/HTTP :: WSGI :: Application
